ArchLab03/ex8/fifo.v
module fifo(clk, reset, in, push, pop, out, full);
   parameter N=4; // determines the maximum number of words in queue.
   parameter M=2; // determines the bit-width of each word, stored in the queue.
   
   localparam zero = 0 ;

   input clk, reset, push, pop;
   input [M-1:0] in;
   output [M-1:0] out;
//    output [M*N-1:0] debug_queue;
   output full;

   
   // Fill Here
   
   reg [M*N-1:0] queue = 0;

   integer n = 0;   // n==0 means empty queue!
   reg [M-1:0] word_out = 0;
   reg is_full = 0;
   
	always @(posedge clk or reset) begin : active
		if(reset == 1) begin : reset_all
			queue <= 0;
			n <= 0;
			is_full <= 0;
			word_out <= 0; 
		end
		else begin : operations

			// word_out <=  (((1 << M) -1) << & queue); // create M times '1' in LSB's and padded with 32-M '0' LSB's

			if (n == 0) begin : empty_queue
				if (push == 1) begin : first_push // verified
					word_out <= in;
					queue <= (in << (M*(N-1))) | queue ;
					n <= 1;
				end else
					if (push == 0) begin: zero_out
						word_out <= zero ;
					end
			end
			else begin
				if( n < N) begin : common_rutine // n from 1 to N-1
					if (pop == 1 && push == 0) begin : pop_common // verified
						word_out <= (queue >>> (N-n)*M) ;
						queue <= ((queue >>> (N-n+1)*M) <<< (N-n+1)*M);
						n <= n - 1;
					end else;
					if (pop == 0 && push == 1) begin : push_common // verified
						word_out <= (queue >>> (N-n)*M) ;
						queue <= (in << (M*(N-1))) | queue >>> M ;
						n <= n + 1;
						if (n == N-1) begin: raise_full
							is_full <= 1'b1;
						end
					end else;
					if (pop == 1 && push == 1) begin : push_pop_common // verified
						word_out <= (queue >>> (N-n)*M) ;
						queue <= (in << (M*(N-1))) | (((queue >>> (N-n+1)*M) <<< (N-n+1)*M) >>> M);
					end else;
					if (pop == 0 && push == 0) begin : nop_common
						n <= n;
						queue <= queue;
					end else;
				end
				else begin : edge_routine
					if(pop == 1 && push == 0) begin : pop_edge  // verified
						word_out <= queue ;
						queue <= ((queue >>> M) <<< M);
						n <= n - 1;
						is_full <= 1'b0;
					end else;
					if(pop == 1 && push == 1) begin : push_pop_edge //verified
						word_out <= queue ;
						queue <= (in << (M*(N-1))) | (queue >>> M); 
					end else;
					if(pop == 0) begin : nop_edge
			
					end else;
				end
			end			
		end
	end
	assign full = is_full;
	// assign debug_queue = queue;
    assign out = word_out;
	
endmodule

Lab03/ex8/fifo_tb.v
module main;
reg clk, reset, push, pop;
reg [1:0] in;
wire [1:0] out;
wire full;
integer fail,print;

// wire [7:0] queue;
// wire[1:0] q3,q2,q1,q0;
// assign q3 = queue[7:6];
// assign q2 = queue[5:4];
// assign q1 = queue[3:2];
// assign q0 = queue[1:0];

fifo #(4,2) fifo_test (clk, reset, in, push, pop, out, full);

always@(print)
    begin : print_trace
		if (pop && ~push) begin : single_pop
			$display("popped %b",out);
		end 
		else if (~pop && push) begin : single_push
				$display ("pushed %b", in);
		end
		else if (pop && push) begin : push_n_pop
				$display ("poped %b & pushed %b", out, in);
		end else
				$display("nothing happend...");
		// $display(" \t > queue: %b %b %b %b \n\t out=%b, full=%b\n %dth cycle\n  ~~~~~~~~~~~~~~~~~~~~~~~~~~~~~~\n", q3,q2,q1,q0,out,full, $time);
    end


initial begin
$dumpfile("waves.vcd");
$dumpvars;
print = 0;
clk = 1; fail = 0;
#10

//reset params
reset = 1;
in = 0;
push = 0; pop = 0; 
#10
print = print +1;
if (full != 0 || out != 0) fail <= 1;

#10 reset =0;

// push 01
#10; push =1; pop = 0; in = 1;  print = print+1; #10; push=0; #20
if (out != 2'b01 || full != 0) fail <= 2;
//push 10
#10; push =1; pop = 0; in = 2;  print = print+1; #10; push=0; #20
if (out != 2'b01 || full != 0) fail <= 3;
// push 11
#10; push =1; pop = 0; in = 3;  print = print+1; #10; push=0; #20
if (out != 2'b01 || full != 0) fail <= 4;
// push 01
#10; push =1; pop = 0; in = 1;  print = print+1; #10; push=0; #20
if (out != 2'b01 || full != 1) fail <= 5;
//push when empty (nop)
#10; push =1; pop = 0; in = 3;  print = print+1; #10; push=0; #20
if (out != 2'b01 || full != 1) fail <= 6;
// pop (01)
#10; pop =1; push = 0; in = 0;  print = print+1; #10; pop=0; #20
if (out != 2'b01 || full != 0) fail <= 7;
// pop (10)
#10; pop =1; push = 0; in = 0;  print = print+1; #10; pop=0; #20
if (out != 2'b10 || full != 0) fail <= 8;
// pop (11) & push (10)
#10; pop =1; push = 1; in = 2;  print = print+1; #10; pop=0; push=0; #20
if (out != 2'b11 || full != 0) fail <= 9;
// pop (01) & push (11)
#10; pop =1; push = 1; in = 3;  print = print+1; #10; pop=0; push=0; #20
if (out != 2'b01 || full != 0) fail <= 10;
// push 01
#10; push =1; pop = 0; in = 1;  print = print+1; #10; push=0; #20
if (out != 2'b10 || full != 0) fail <= 11;
//push 10
#10; push =1; pop = 0; in = 2;  print = print+1; #10; push=0; #20
if (out != 2'b10 || full != 1) fail <= 12;
// pop (10) & push (00)
#10; pop =1; push = 1; in = 0 ;  print = print+1; #10; pop=0; push=0; #20
if (out != 2'b10 || full != 1) fail <= 13;
// pop (11) & push (01)
#10; pop =1; push = 1; in = 1 ;  print = print+1; #10; pop=0; push=0; #20
if (out != 2'b11 || full != 1) fail <= 13;


#10 
if(fail == 0)
	$display("PASSED ALL TESTS");
else
	$display("DID NOT PASS ALL TESTS. last failed in %d:", fail);
	
$finish;
end
always #5 clk = ~clk;
endmodule

Lab03/ex8/waves.vcd
$date
    Nov 16, 2021  09:33:30
$end
$version
    TOOL:	ncsim(64)	15.20-s085
$end
$timescale
    1 ns
$end

$scope module main $end
$var reg       1 !    clk  $end
$var reg       1 "    reset  $end
$var reg       1 #    push  $end
$var reg       1 $    pop  $end
$var reg       2 %    in [1:0] $end
$var wire      2 &    out [1:0] $end
$var wire      1 '    full  $end
$var integer  32 (    fail  $end
$var integer  32 )    print  $end

$scope module fifo_test $end
$var parameter 32 *    N  $end
$var parameter 32 +    M  $end
$var parameter 32 ,    zero  $end
$var wire      1 -    clk  $end
$var wire      1 .    reset  $end
$var wire      1 /    push  $end
$var wire      1 0    pop  $end
$var wire      2 1    in [1:0] $end
$var wire      2 &    out [1:0] $end
$var wire      1 '    full  $end
$var reg       8 2    queue [7:0] $end
$var integer  32 3    n  $end
$var reg       2 4    word_out [1:0] $end
$var reg       1 5    is_full  $end
$upscope $end

$upscope $end

$enddefinitions $end
$dumpvars
b0 ,
b10 +
b100 *
1!
x"
x#
x$
bx %
b0 &
0'
b0 (
b0 )
1-
x.
x/
x0
bx 1
b0 2
b0 3
b0 4
05
$end
#5
0!
0-
#10
1"
b0 %
0#
0$
1!
1-
00
0/
b0 1
1.
#15
0!
0-
#20
b1 )
1!
1-
#25
0!
0-
#30
0"
1!
1-
0.
#35
0!
0-
#40
1#
b1 %
b10 )
1!
1-
b1 1
1/
b1 4
b1000000 2
b1 3
b1 &
#45
0!
0-
#50
0#
1!
1-
0/
#55
0!
0-
#60
1!
1-
#65
0!
0-
#70
1!
1-
#75
0!
0-
#80
1#
b10 %
b11 )
1!
1-
b10 1
1/
b10010000 2
b10 3
#85
0!
0-
#90
0#
1!
1-
0/
#95
0!
0-
#100
1!
1-
#105
0!
0-
#110
1!
1-
#115
0!
0-
#120
1#
b11 %
b100 )
1!
1-
b11 1
1/
b11100100 2
b11 3
#125
0!
0-
#130
0#
1!
1-
0/
#135
0!
0-
#140
1!
1-
#145
0!
0-
#150
1!
1-
#155
0!
0-
#160
1#
b1 %
b101 )
1!
1-
b1 1
1/
b1111001 2
b100 3
15
1'
#165
0!
0-
#170
0#
1!
1-
0/
#175
0!
0-
#180
1!
1-
#185
0!
0-
#190
1!
1-
#195
0!
0-
#200
1#
b11 %
b110 )
1!
1-
b11 1
1/
#205
0!
0-
#210
0#
1!
1-
0/
#215
0!
0-
#220
1!
1-
#225
0!
0-
#230
1!
1-
#235
0!
0-
#240
1$
b0 %
b111 )
1!
1-
b0 1
10
b1111000 2
b11 3
05
0'
#245
0!
0-
#250
0$
1!
1-
00
#255
0!
0-
#260
1!
1-
#265
0!
0-
#270
1!
1-
#275
0!
0-
#280
1$
b1000 )
1!
1-
10
b10 4
b1110000 2
b10 3
b10 &
#285
0!
0-
#290
0$
1!
1-
00
#295
0!
0-
#300
1!
1-
#305
0!
0-
#310
1!
1-
#315
0!
0-
#320
1$
1#
b10 %
b1001 )
1!
1-
b10 1
1/
10
b11 4
b10010000 2
b11 &
#325
0!
0-
#330
0$
0#
1!
1-
0/
00
#335
0!
0-
#340
1!
1-
#345
0!
0-
#350
1!
1-
#355
0!
0-
#360
1$
1#
b11 %
b1010 )
1!
1-
b11 1
1/
10
b1 4
b11100000 2
b1 &
#365
0!
0-
#370
0$
0#
1!
1-
0/
00
#375
0!
0-
#380
1!
1-
#385
0!
0-
#390
1!
1-
#395
0!
0-
#400
1#
b1 %
b1011 )
1!
1-
b1 1
1/
b10 4
b1111000 2
b11 3
b10 &
#405
0!
0-
#410
0#
1!
1-
0/
#415
0!
0-
#420
1!
1-
#425
0!
0-
#430
1!
1-
#435
0!
0-
#440
1#
b10 %
b1100 )
1!
1-
b10 1
1/
b10011110 2
b100 3
15
1'
#445
0!
0-
#450
0#
1!
1-
0/
#455
0!
0-
#460
1!
1-
#465
0!
0-
#470
1!
1-
#475
0!
0-
#480
1$
1#
b0 %
b1101 )
1!
1-
b0 1
1/
10
b100111 2
#485
0!
0-
#490
0$
0#
1!
1-
0/
00
#495
0!
0-
#500
1!
1-
#505
0!
0-
#510
1!
1-
#515
0!
0-
#520
1$
1#
b1 %
b1110 )
1!
1-
b1 1
1/
10
b11 4
b1001001 2
b11 &
#525
0!
0-
#530
0$
0#
1!
1-
0/
00
