Lab03/ex6/parity.v
module parity(clk, in, reset, out);

  input clk, in, reset;
  output out;

  reg 	  out;
  reg 	  state;

  localparam zero=0, one=1;

  always @(posedge clk)
    begin
	    if (reset)
	      state <= zero;
	    else
	      case (state)
	        0: state <= in;         // if state is 0 change state to input  (xor(0,in) = in )
          1: state <= ~in         // if state is 1 change state to ~input (xor(1,in) = ~in)
          default: state <= one;  // default is even (start at zero)
	      endcase
    end

  always @(state) //update output
    begin
	    case (state)
	      0: out <= zero;
        1: out <= one;
        default: out <= one;
	    endcase
    end

endmodule

Lab03/ex6/parity_tb.v
module main;
   reg in, clk, reset;
   wire out;

   parity par(clk, in, reset, out)

   always #5 clk = ~clk;

   always @(negedge clk)
     begin
	if (!reset)
          $display("time %d: in %b, out %b", $time, in, out);
	in = ($random / 16) % 2;
     end
   
   initial
     begin
        $dumpfile("waves.vcd");
        $dumpvars;
        clk = 0;
	in = 0;
        reset = 1;
        #10
	reset = 0;
        #300;
	@(negedge clk);
	#1;
	if (out == 1)
	  $display("ACCEPT");
        $finish;
     end // initial begin
endmodule

Lab03/ex6/waves.vcd
$date
    Nov 16, 2021  09:32:15
$end
$version
    TOOL:	ncsim(64)	15.20-s085
$end
$timescale
    1 ns
$end

$scope module main $end
$var reg       1 !    in  $end
$var reg       1 "    clk  $end
$var reg       1 #    reset  $end
$var wire      1 $    out  $end

$scope module par $end
$var wire      1 %    clk  $end
$var wire      1 &    in  $end
$var wire      1 '    reset  $end
$var reg       1 (    out  $end
$var reg       1 )    state  $end
$var parameter 32 *    zero  $end
$var parameter 32 +    one  $end
$upscope $end

$upscope $end

$enddefinitions $end
$dumpvars
b1 +
b0 *
0!
0"
1#
x$
0%
0&
1'
x(
x)
$end
#5
1"
1%
0)
0(
0$
#10
0#
0"
1!
1&
0%
0'
#15
1"
1%
1)
1(
1$
#20
0"
0%
#25
1"
1%
0)
0(
0$
#30
0"
0%
#35
1"
1%
1)
1(
1$
#40
0"
0!
0&
0%
#45
1"
1%
#50
0"
0%
#55
1"
1%
#60
0"
1!
1&
0%
#65
1"
1%
0)
0(
0$
#70
0"
0!
0&
0%
#75
1"
1%
#80
0"
0%
#85
1"
1%
#90
0"
0%
#95
1"
1%
#100
0"
1!
1&
0%
#105
1"
1%
1)
1(
1$
#110
0"
0%
#115
1"
1%
0)
0(
0$
#120
0"
0!
0&
0%
#125
1"
1%
#130
0"
0%
#135
1"
1%
#140
0"
1!
1&
0%
#145
1"
1%
1)
1(
1$
#150
0"
0%
#155
1"
1%
0)
0(
0$
#160
0"
0%
#165
1"
1%
1)
1(
1$
#170
0"
0%
#175
1"
1%
0)
0(
0$
#180
0"
0!
0&
0%
#185
1"
1%
#190
0"
0%
#195
1"
1%
#200
0"
0%
#205
1"
1%
#210
0"
0%
#215
1"
1%
#220
0"
1!
1&
0%
#225
1"
1%
1)
1(
1$
#230
0"
0%
#235
1"
1%
0)
0(
0$
#240
0"
0%
#245
1"
1%
1)
1(
1$
#250
0"
0%
#255
1"
1%
0)
0(
0$
#260
0"
0%
#265
1"
1%
1)
1(
1$
#270
0"
0!
0&
0%
#275
1"
1%
#280
0"
1!
1&
0%
#285
1"
1%
0)
0(
0$
#290
0"
0%
#295
1"
1%
1)
1(
1$
#300
0"
0%
#305
1"
1%
0)
0(
0$
#310
0"
0!
0&
0%
