ArchLab03/ex3/fulladder.v
module fulladder( sum, co, a, b, ci);

  input   a, b, ci;
  output  sum, co;

  wire x,y,z;

  xor(x, a, b);
  xor(sum, x, ci);
  and(y, x, ci);
  and(z, a, b);
  or(co, y, z);
  

endmodule

Lab03/ex4/add4.v
module  add4( sum, co, a, b, ci);

  input   [3:0] a, b;
  input   ci;
  output  [3:0] sum;
  output  co;
  wire c0, c1, c2;
  // module fulladder( sum, co, a, b, ci);

  fulladder fa0(sum[0], c0, a[0], b[0], ci);
  fulladder fa1(sum[1], c1, a[1], b[1], c0);
  fulladder fa2(sum[2], c2, a[2], b[2], c1);
  fulladder fa3(sum[3], co, a[3], b[3], c2);



endmodule

Lab03/ex5/addsub.v
module	addsub( result, operand_a, operand_b, mode );

	input	[3:0]	operand_a, operand_b;
	input	mode;
	output	[3:0]	result;
	wire co;
	wire	[3:0]	xor_b;


	xor	g0(xor_b[0], operand_b[0], mode);
	xor	g1(xor_b[1], operand_b[1], mode);
	xor	g2(xor_b[2], operand_b[2], mode);
	xor	g3(xor_b[3], operand_b[3], mode);

	
	add4	m1(
		.sum(result),
		.co(co),
		.a(operand_a),	 
		.b(xor_b),	
		.ci(mode)
	);	
endmodule

Lab03/ex5/addsub_tb.v
module	addsub_tb;
	
	// for DUT port connection
	reg					mode;
	reg 	[3:0]	operand_a, operand_b;
	wire	[3:0] result;
	wire co;
	
	// for pattern generation
	integer			a, b, expect, error_num, t;
	reg					overflow;
	wire	[3:0]	expect_out = expect[3:0];	// compare "expect_out" with "result"

	// FILL here
	addsub addsub( result, operand_a, operand_b, mode );

	// give stimulus pattern
	initial begin
	error_num = 0;

	$dumpfile("waves.vcd");
	$dumpvars;

	$display( "\nTest subtraction mode." );
	#10 mode = 1'b1;
	
	for( a=-8; a<=7; a=a+1 ) begin
		for( b=-8; b<=7; b=b+1 ) begin
			
			operand_a = a[3:0];
			operand_b = b[3:0];
			expect = a - b;
	
			#1;
			if( expect >= -8 && expect <= 7 ) begin
				overflow = 1'b0;
				if( expect[3:0] !== result ) begin
					error_num = error_num + 1;
					$display( "Error(%d):(%d)-(%d) Expect(%b) Output(%b)", error_num[9:0], a, b, expect[3:0], result );
				end
			end	else begin
				overflow = 1'b1;
			end
	
			#1;
		end
	end

	$display( "\nTest addition mode." );
	mode = 1'b0;
	
	for( a=-8; a<=7; a=a+1 ) begin
		for( b=-8; b<=7; b=b+1 ) begin
			
			operand_a = a[3:0];
			operand_b = b[3:0];
			expect = a + b;
	
			#1;
			if( expect >= -8 && expect <= 7 ) begin
				overflow = 1'b0;
				if( expect[3:0] !== result ) begin
					error_num = error_num + 1;
					$display( "Error(%d):(%d)+(%d) Expect(%b) Output(%b)", error_num[9:0], a, b, expect[3:0], result );
				end
			end	else begin
				overflow = 1'b1;
			end
	
			#1;
		end
	end
	
	if( error_num==0 )
		$display( "\nPass all test\n" );
	else
		$display( "\nFail, error number = %d\n", error_num );
	
	#10 $finish;
	end

endmodule

Lab03/ex5/waves.vcd
$date
    Nov 16, 2021  09:30:22
$end
$version
    TOOL:	ncsim(64)	15.20-s085
$end
$timescale
    1 ns
$end

$scope module addsub_tb $end
$var reg       1 !    mode  $end
$var reg       4 "    operand_a [3:0] $end
$var reg       4 #    operand_b [3:0] $end
$var wire      1 $    result [3] $end
$var wire      1 %    result [2] $end
$var wire      1 &    result [1] $end
$var wire      1 '    result [0] $end
$var integer  32 (    a  $end
$var integer  32 )    b  $end
$var integer  32 *    expect  $end
$var integer  32 +    error_num  $end
$var reg       1 ,    overflow  $end
$var wire      4 -    expect_out [3:0] $end

$scope module addsub $end
$var wire      1 .    operand_a [3] $end
$var wire      1 /    operand_a [2] $end
$var wire      1 0    operand_a [1] $end
$var wire      1 1    operand_a [0] $end
$var wire      1 2    operand_b [3] $end
$var wire      1 3    operand_b [2] $end
$var wire      1 4    operand_b [1] $end
$var wire      1 5    operand_b [0] $end
$var wire      1 6    mode  $end
$var wire      1 $    result [3] $end
$var wire      1 %    result [2] $end
$var wire      1 &    result [1] $end
$var wire      1 '    result [0] $end
$var wire      1 7    co  $end
$var wire      1 8    xor_b [3] $end
$var wire      1 9    xor_b [2] $end
$var wire      1 :    xor_b [1] $end
$var wire      1 ;    xor_b [0] $end

$scope module m1 $end
$var wire      1 .    a [3] $end
$var wire      1 /    a [2] $end
$var wire      1 0    a [1] $end
$var wire      1 1    a [0] $end
$var wire      1 8    b [3] $end
$var wire      1 9    b [2] $end
$var wire      1 :    b [1] $end
$var wire      1 ;    b [0] $end
$var wire      1 6    ci  $end
$var wire      1 $    sum [3] $end
$var wire      1 %    sum [2] $end
$var wire      1 &    sum [1] $end
$var wire      1 '    sum [0] $end
$var wire      1 7    co  $end
$var wire      1 <    c0  $end
$var wire      1 =    c1  $end
$var wire      1 >    c2  $end

$scope module fa0 $end
$var wire      1 1    a  $end
$var wire      1 ;    b  $end
$var wire      1 6    ci  $end
$var wire      1 '    sum  $end
$var wire      1 <    co  $end
$var wire      1 ?    x  $end
$var wire      1 @    y  $end
$var wire      1 A    z  $end
$upscope $end


$scope module fa1 $end
$var wire      1 0    a  $end
$var wire      1 :    b  $end
$var wire      1 <    ci  $end
$var wire      1 &    sum  $end
$var wire      1 =    co  $end
$var wire      1 B    x  $end
$var wire      1 C    y  $end
$var wire      1 D    z  $end
$upscope $end


$scope module fa2 $end
$var wire      1 /    a  $end
$var wire      1 9    b  $end
$var wire      1 =    ci  $end
$var wire      1 %    sum  $end
$var wire      1 >    co  $end
$var wire      1 E    x  $end
$var wire      1 F    y  $end
$var wire      1 G    z  $end
$upscope $end


$scope module fa3 $end
$var wire      1 .    a  $end
$var wire      1 8    b  $end
$var wire      1 >    ci  $end
$var wire      1 $    sum  $end
$var wire      1 7    co  $end
$var wire      1 H    x  $end
$var wire      1 I    y  $end
$var wire      1 J    z  $end
$upscope $end

$upscope $end

$upscope $end

$upscope $end

$enddefinitions $end
$dumpvars
x!
bx "
bx #
x$
x%
x&
x'
bx (
bx )
bx *
b0 +
x,
bx -
x.
x/
x0
x1
x2
x3
x4
x5
x6
x7
x8
x9
x:
x;
x<
x=
x>
x?
x@
xA
xB
xC
xD
xE
xF
xG
xH
xI
xJ
$end
#10
1!
b11111111111111111111111111111000 (
b11111111111111111111111111111000 )
b1000 "
b1000 #
b0 *
b0 -
12
03
04
05
1.
0/
00
01
16
08
19
1:
1;
0A
0D
0G
0J
1?
1B
1E
1H
0'
1@
1<
0&
1C
1=
0%
1F
1>
0$
1I
17
#11
0,
#12
b11111111111111111111111111111001 )
b1001 #
b11111111111111111111111111111111 *
b1111 -
15
0;
0?
0@
0<
1&
0C
0=
1'
1%
0F
0>
1$
0I
07
#14
b11111111111111111111111111111010 )
b1010 #
b11111111111111111111111111111110 *
b1110 -
14
05
1;
0:
0B
1?
1@
1<
0'
#16
b11111111111111111111111111111011 )
b1011 #
b11111111111111111111111111111101 *
b1101 -
15
0;
0?
0@
0<
0&
1'
#18
b11111111111111111111111111111100 )
b1100 #
b11111111111111111111111111111100 *
b1100 -
13
04
05
1;
1:
09
0E
1B
1?
1@
1<
1C
1=
0'
#20
b11111111111111111111111111111101 )
b1101 #
b11111111111111111111111111111011 *
b1011 -
15
0;
0?
0@
0<
1&
0C
0=
1'
0%
#22
b11111111111111111111111111111110 )
b1110 #
b11111111111111111111111111111010 *
b1010 -
14
05
1;
0:
0B
1?
1@
1<
0'
#24
b11111111111111111111111111111111 )
b1111 #
b11111111111111111111111111111001 *
b1001 -
15
0;
0?
0@
0<
0&
1'
#26
b0 )
b0 #
b11111111111111111111111111111000 *
b1000 -
02
03
04
05
1;
1:
19
18
0H
1J
17
1E
1B
1?
1@
1<
1C
1=
0'
1$
1F
1>
#28
b1 )
b1 #
b11111111111111111111111111110111 *
b111 -
15
0;
0?
0@
0<
1&
0C
0=
1'
1%
0F
0>
0$
#29
1,
#30
b10 )
b10 #
b11111111111111111111111111110110 *
b110 -
14
05
1;
0:
0B
1?
1@
1<
0'
#32
b11 )
b11 #
b11111111111111111111111111110101 *
b101 -
15
0;
0?
0@
0<
0&
1'
#34
b100 )
b100 #
b11111111111111111111111111110100 *
b100 -
13
04
05
1;
1:
09
0E
1B
1?
1@
1<
1C
1=
0'
#36
b101 )
b101 #
b11111111111111111111111111110011 *
b11 -
15
0;
0?
0@
0<
1&
0C
0=
1'
0%
#38
b110 )
b110 #
b11111111111111111111111111110010 *
b10 -
14
05
1;
0:
0B
1?
1@
1<
0'
#40
b111 )
b111 #
b11111111111111111111111111110001 *
b1 -
15
0;
0?
0@
0<
0&
1'
#42
b1000 )
b11111111111111111111111111111001 (
b11111111111111111111111111111000 )
b1001 "
b1000 #
b1 *
12
03
04
05
11
0?
0@
1<
1;
1:
19
08
1H
0J
17
1E
1B
1A
1C
1=
1F
1>
1I
#43
0,
#44
b11111111111111111111111111111001 )
b1001 #
b0 *
b0 -
15
0;
1?
0A
1@
0'
#46
b11111111111111111111111111111010 )
b1010 #
b11111111111111111111111111111111 *
b1111 -
14
05
1;
0:
0B
0C
0=
0?
1A
0@
1'
1%
0F
0>
1&
1$
0I
07
#48
b11111111111111111111111111111011 )
b1011 #
b11111111111111111111111111111110 *
b1110 -
15
0;
1?
0A
1@
0'
#50
b11111111111111111111111111111100 )
b1100 #
b11111111111111111111111111111101 *
b1101 -
13
04
05
1;
1:
09
0E
1B
1C
1=
0?
1A
0@
1'
0&
#52
b11111111111111111111111111111101 )
b1101 #
b11111111111111111111111111111100 *
b1100 -
15
0;
1?
0A
1@
0'
#54
b11111111111111111111111111111110 )
b1110 #
b11111111111111111111111111111011 *
b1011 -
14
05
1;
0:
0B
0C
0=
0?
1A
0@
1'
0%
1&
#56
b11111111111111111111111111111111 )
b1111 #
b11111111111111111111111111111010 *
b1010 -
15
0;
1?
0A
1@
0'
#58
b0 )
b0 #
b11111111111111111111111111111001 *
b1001 -
02
03
04
05
1;
1:
19
18
0H
1J
17
1E
1B
1C
1=
0?
1A
0@
1'
1F
1>
0&
#60
b1 )
b1 #
b11111111111111111111111111111000 *
b1000 -
15
0;
1?
0A
1@
0'
#62
b10 )
b10 #
b11111111111111111111111111110111 *
b111 -
14
05
1;
0:
0B
0C
0=
0?
1A
0@
1'
1%
0F
0>
1&
0$
#63
1,
#64
b11 )
b11 #
b11111111111111111111111111110110 *
b110 -
15
0;
1?
0A
1@
0'
#66
b100 )
b100 #
b11111111111111111111111111110101 *
b101 -
13
04
05
1;
1:
09
0E
1B
1C
1=
0?
1A
0@
1'
0&
#68
b101 )
b101 #
b11111111111111111111111111110100 *
b100 -
15
0;
1?
0A
1@
0'
#70
b110 )
b110 #
b11111111111111111111111111110011 *
b11 -
14
05
1;
0:
0B
0C
0=
0?
1A
0@
1'
0%
1&
#72
b111 )
b111 #
b11111111111111111111111111110010 *
b10 -
15
0;
1?
0A
1@
0'
#74
b1000 )
b11111111111111111111111111111010 (
b11111111111111111111111111111000 )
b1010 "
b1000 #
b10 *
12
03
04
05
10
01
1?
1@
1<
0B
1;
1:
19
08
1H
0J
17
1E
1D
1=
1F
1>
1I
#75
0,
#76
b11111111111111111111111111111001 )
b1001 #
b1 *
b1 -
15
0;
0?
0@
0<
0&
1'
#78
b11111111111111111111111111111010 )
b1010 #
b0 *
b0 -
14
05
1;
0:
1B
0D
1=
1?
1@
1<
1C
0'
#80
b11111111111111111111111111111011 )
b1011 #
b11111111111111111111111111111111 *
b1111 -
15
0;
0?
0@
0<
1&
0C
0=
1'
1%
0F
0>
1$
0I
07
#82
b11111111111111111111111111111100 )
b1100 #
b11111111111111111111111111111110 *
b1110 -
13
04
05
1;
1:
09
0E
0B
1D
1=
1?
1@
1<
0'
#84
b11111111111111111111111111111101 )
b1101 #
b11111111111111111111111111111101 *
b1101 -
15
0;
0?
0@
0<
0&
1'
#86
b11111111111111111111111111111110 )
b1110 #
b11111111111111111111111111111100 *
b1100 -
14
05
1;
0:
1B
0D
1=
1?
1@
1<
1C
0'
#88
b11111111111111111111111111111111 )
b1111 #
b11111111111111111111111111111011 *
b1011 -
15
0;
0?
0@
0<
1&
0C
0=
1'
0%
#90
b0 )
b0 #
b11111111111111111111111111111010 *
b1010 -
02
03
04
05
1;
1:
19
18
0H
1J
17
1E
0B
1D
1=
1?
1@
1<
0'
1F
1>
#92
b1 )
b1 #
b11111111111111111111111111111001 *
b1001 -
15
0;
0?
0@
0<
0&
1'
#94
b10 )
b10 #
b11111111111111111111111111111000 *
b1000 -
14
05
1;
0:
1B
0D
1=
1?
1@
1<
1C
0'
#96
b11 )
b11 #
b11111111111111111111111111110111 *
b111 -
15
0;
0?
0@
0<
1&
0C
0=
1'
1%
0F
0>
0$
#97
1,
#98
b100 )
b100 #
b11111111111111111111111111110110 *
b110 -
13
04
05
1;
1:
09
0E
0B
1D
1=
1?
1@
1<
0'
#100
b101 )
b101 #
b11111111111111111111111111110101 *
b101 -
15
0;
0?
0@
0<
0&
1'
#102
b110 )
b110 #
b11111111111111111111111111110100 *
b100 -
14
05
1;
0:
1B
0D
1=
1?
1@
1<
1C
0'
#104
b111 )
b111 #
b11111111111111111111111111110011 *
b11 -
15
0;
0?
0@
0<
1&
0C
0=
1'
0%
#106
b1000 )
b11111111111111111111111111111011 (
b11111111111111111111111111111000 )
b1011 "
b1000 #
b11 *
12
03
04
05
11
0?
0@
1<
1;
1:
19
08
1H
0J
17
1E
0B
1A
1D
1=
1F
1>
1I
#107
0,
#108
b11111111111111111111111111111001 )
b1001 #
b10 *
b10 -
15
0;
1?
0A
1@
0'
#110
b11111111111111111111111111111010 )
b1010 #
b1 *
b1 -
14
05
1;
0:
1B
0D
1C
0?
1A
0@
1'
0&
#112
b11111111111111111111111111111011 )
b1011 #
b0 *
b0 -
15
0;
1?
0A
1@
0'
#114
b11111111111111111111111111111100 )
b1100 #
b11111111111111111111111111111111 *
b1111 -
13
04
05
1;
1:
09
0E
0F
0>
0B
1D
0C
0?
1A
0@
1'
1&
1$
0I
07
1%
#116
b11111111111111111111111111111101 )
b1101 #
b11111111111111111111111111111110 *
b1110 -
15
0;
1?
0A
1@
0'
#118
b11111111111111111111111111111110 )
b1110 #
b11111111111111111111111111111101 *
b1101 -
14
05
1;
0:
1B
0D
1C
0?
1A
0@
1'
0&
#120
b11111111111111111111111111111111 )
b1111 #
b11111111111111111111111111111100 *
b1100 -
15
0;
1?
0A
1@
0'
#122
b0 )
b0 #
b11111111111111111111111111111011 *
b1011 -
02
03
04
05
1;
1:
19
18
0H
1J
17
1E
1F
1>
0B
1D
0C
0?
1A
0@
1'
1&
0%
#124
b1 )
b1 #
b11111111111111111111111111111010 *
b1010 -
15
0;
1?
0A
1@
0'
#126
b10 )
b10 #
b11111111111111111111111111111001 *
b1001 -
14
05
1;
0:
1B
0D
1C
0?
1A
0@
1'
0&
#128
b11 )
b11 #
b11111111111111111111111111111000 *
b1000 -
15
0;
1?
0A
1@
0'
#130
b100 )
b100 #
b11111111111111111111111111110111 *
b111 -
13
04
05
1;
1:
09
0E
0F
0>
0B
1D
0C
0?
1A
0@
1'
1&
0$
1%
#131
1,
#132
b101 )
b101 #
b11111111111111111111111111110110 *
b110 -
15
0;
1?
0A
1@
0'
#134
b110 )
b110 #
b11111111111111111111111111110101 *
b101 -
14
05
1;
0:
1B
0D
1C
0?
1A
0@
1'
0&
#136
b111 )
b111 #
b11111111111111111111111111110100 *
b100 -
15
0;
1?
0A
1@
0'
#138
b1000 )
b11111111111111111111111111111100 (
b11111111111111111111111111111000 )
b1100 "
b1000 #
b100 *
12
03
04
05
1/
00
01
1?
1@
1<
1B
1C
1=
0E
1;
1:
19
08
1H
0J
17
1G
1>
1%
1I
#139
0,
#140
b11111111111111111111111111111001 )
b1001 #
b11 *
b11 -
15
0;
0?
0@
0<
1&
0C
0=
1'
0%
#142
b11111111111111111111111111111010 )
b1010 #
b10 *
b10 -
14
05
1;
0:
0B
1?
1@
1<
0'
#144
b11111111111111111111111111111011 )
b1011 #
b1 *
b1 -
15
0;
0?
0@
0<
0&
1'
#146
b11111111111111111111111111111100 )
b1100 #
b0 *
b0 -
13
04
05
1;
1:
09
1E
0G
1>
1B
1?
1@
1<
1C
1=
0'
0$
1I
17
1F
#148
b11111111111111111111111111111101 )
b1101 #
b11111111111111111111111111111111 *
b1111 -
15
0;
0?
0@
0<
1&
0C
0=
1'
1%
0F
0>
1$
0I
07
#150
b11111111111111111111111111111110 )
b1110 #
b11111111111111111111111111111110 *
b1110 -
14
05
1;
0:
0B
1?
1@
1<
0'
#152
b11111111111111111111111111111111 )
b1111 #
b11111111111111111111111111111101 *
b1101 -
15
0;
0?
0@
0<
0&
1'
#154
b0 )
b0 #
b11111111111111111111111111111100 *
b1100 -
02
03
04
05
1;
1:
19
18
0H
1J
17
0E
1G
1>
1B
1?
1@
1<
1C
1=
0'
#156
b1 )
b1 #
b11111111111111111111111111111011 *
b1011 -
15
0;
0?
0@
0<
1&
0C
0=
1'
0%
#158
b10 )
b10 #
b11111111111111111111111111111010 *
b1010 -
14
05
1;
0:
0B
1?
1@
1<
0'
#160
b11 )
b11 #
b11111111111111111111111111111001 *
b1001 -
15
0;
0?
0@
0<
0&
1'
#162
b100 )
b100 #
b11111111111111111111111111111000 *
b1000 -
13
04
05
1;
1:
09
1E
0G
1>
1B
1?
1@
1<
1C
1=
0'
1$
1F
#164
b101 )
b101 #
b11111111111111111111111111110111 *
b111 -
15
0;
0?
0@
0<
1&
0C
0=
1'
1%
0F
0>
0$
#165
1,
#166
b110 )
b110 #
b11111111111111111111111111110110 *
b110 -
14
05
1;
0:
0B
1?
1@
1<
0'
#168
b111 )
b111 #
b11111111111111111111111111110101 *
b101 -
15
0;
0?
0@
0<
0&
1'
#170
b1000 )
b11111111111111111111111111111101 (
b11111111111111111111111111111000 )
b1101 "
b1000 #
b101 *
12
03
04
05
11
0?
0@
1<
1;
1:
19
08
1H
0J
17
0E
1G
1>
1B
1A
1C
1=
1I
#171
0,
#172
b11111111111111111111111111111001 )
b1001 #
b100 *
b100 -
15
0;
1?
0A
1@
0'
#174
b11111111111111111111111111111010 )
b1010 #
b11 *
b11 -
14
05
1;
0:
0B
0C
0=
0?
1A
0@
1'
0%
1&
#176
b11111111111111111111111111111011 )
b1011 #
b10 *
b10 -
15
0;
1?
0A
1@
0'
#178
b11111111111111111111111111111100 )
b1100 #
b1 *
b1 -
13
04
05
1;
1:
09
1E
0G
1>
1B
1C
1=
0?
1A
0@
1'
1F
0&
#180
b11111111111111111111111111111101 )
b1101 #
b0 *
b0 -
15
0;
1?
0A
1@
0'
#182
b11111111111111111111111111111110 )
b1110 #
b11111111111111111111111111111111 *
b1111 -
14
05
1;
0:
0B
0C
0=
0?
1A
0@
1'
1%
0F
0>
1&
1$
0I
07
#184
b11111111111111111111111111111111 )
b1111 #
b11111111111111111111111111111110 *
b1110 -
15
0;
1?
0A
1@
0'
#186
b0 )
b0 #
b11111111111111111111111111111101 *
b1101 -
02
03
04
05
1;
1:
19
18
0H
1J
17
0E
1G
1>
1B
1C
1=
0?
1A
0@
1'
0&
#188
b1 )
b1 #
b11111111111111111111111111111100 *
b1100 -
15
0;
1?
0A
1@
0'
#190
b10 )
b10 #
b11111111111111111111111111111011 *
b1011 -
14
05
1;
0:
0B
0C
0=
0?
1A
0@
1'
0%
1&
#192
b11 )
b11 #
b11111111111111111111111111111010 *
b1010 -
15
0;
1?
0A
1@
0'
#194
b100 )
b100 #
b11111111111111111111111111111001 *
b1001 -
13
04
05
1;
1:
09
1E
0G
1>
1B
1C
1=
0?
1A
0@
1'
1F
0&
#196
b101 )
b101 #
b11111111111111111111111111111000 *
b1000 -
15
0;
1?
0A
1@
0'
#198
b110 )
b110 #
b11111111111111111111111111110111 *
b111 -
14
05
1;
0:
0B
0C
0=
0?
1A
0@
1'
1%
0F
0>
1&
0$
#199
1,
#200
b111 )
b111 #
b11111111111111111111111111110110 *
b110 -
15
0;
1?
0A
1@
0'
#202
b1000 )
b11111111111111111111111111111110 (
b11111111111111111111111111111000 )
b1110 "
b1000 #
b110 *
12
03
04
05
10
01
1?
1@
1<
0B
1;
1:
19
08
1H
0J
17
0E
1G
1>
1D
1=
1I
#203
0,
#204
b11111111111111111111111111111001 )
b1001 #
b101 *
b101 -
15
0;
0?
0@
0<
0&
1'
#206
b11111111111111111111111111111010 )
b1010 #
b100 *
b100 -
14
05
1;
0:
1B
0D
1=
1?
1@
1<
1C
0'
#208
b11111111111111111111111111111011 )
b1011 #
b11 *
b11 -
15
0;
0?
0@
0<
1&
0C
0=
1'
0%
#210
b11111111111111111111111111111100 )
b1100 #
b10 *
b10 -
13
04
05
1;
1:
09
1E
0G
1>
0B
1D
1=
1?
1@
1<
0'
1F
#212
b11111111111111111111111111111101 )
b1101 #
b1 *
b1 -
15
0;
0?
0@
0<
0&
1'
#214
b11111111111111111111111111111110 )
b1110 #
b0 *
b0 -
14
05
1;
0:
1B
0D
1=
1?
1@
1<
1C
0'
#216
b11111111111111111111111111111111 )
b1111 #
b11111111111111111111111111111111 *
b1111 -
15
0;
0?
0@
0<
1&
0C
0=
1'
1%
0F
0>
1$
0I
07
#218
b0 )
b0 #
b11111111111111111111111111111110 *
b1110 -
02
03
04
05
1;
1:
19
18
0H
1J
17
0E
1G
1>
0B
1D
1=
1?
1@
1<
0'
#220
b1 )
b1 #
b11111111111111111111111111111101 *
b1101 -
15
0;
0?
0@
0<
0&
1'
#222
b10 )
b10 #
b11111111111111111111111111111100 *
b1100 -
14
05
1;
0:
1B
0D
1=
1?
1@
1<
1C
0'
#224
b11 )
b11 #
b11111111111111111111111111111011 *
b1011 -
15
0;
0?
0@
0<
1&
0C
0=
1'
0%
#226
b100 )
b100 #
b11111111111111111111111111111010 *
b1010 -
13
04
05
1;
1:
09
1E
0G
1>
0B
1D
1=
1?
1@
1<
0'
1F
#228
b101 )
b101 #
b11111111111111111111111111111001 *
b1001 -
15
0;
0?
0@
0<
0&
1'
#230
b110 )
b110 #
b11111111111111111111111111111000 *
b1000 -
14
05
1;
0:
1B
0D
1=
1?
1@
1<
1C
0'
#232
b111 )
b111 #
b11111111111111111111111111110111 *
b111 -
15
0;
0?
0@
0<
1&
0C
0=
1'
1%
0F
0>
0$
#233
1,
#234
b1000 )
b11111111111111111111111111111111 (
b11111111111111111111111111111000 )
b1111 "
b1000 #
b111 *
12
03
04
05
11
0?
0@
1<
1;
1:
19
08
1H
0J
17
0E
1G
1>
0B
1A
1D
1=
1I
#235
0,
#236
b11111111111111111111111111111001 )
b1001 #
b110 *
b110 -
15
0;
1?
0A
1@
0'
#238
b11111111111111111111111111111010 )
b1010 #
b101 *
b101 -
14
05
1;
0:
1B
0D
1C
0?
1A
0@
1'
0&
#240
b11111111111111111111111111111011 )
b1011 #
b100 *
b100 -
15
0;
1?
0A
1@
0'
#242
b11111111111111111111111111111100 )
b1100 #
b11 *
b11 -
13
04
05
1;
1:
09
1E
0G
1F
0B
1D
0C
0?
1A
0@
1'
1&
0%
#244
b11111111111111111111111111111101 )
b1101 #
b10 *
b10 -
15
0;
1?
0A
1@
0'
#246
b11111111111111111111111111111110 )
b1110 #
b1 *
b1 -
14
05
1;
0:
1B
0D
1C
0?
1A
0@
1'
0&
#248
b11111111111111111111111111111111 )
b1111 #
b0 *
b0 -
15
0;
1?
0A
1@
0'
#250
b0 )
b0 #
b11111111111111111111111111111111 *
b1111 -
02
03
04
05
1;
1:
19
18
0H
1J
0I
0E
1G
0F
0B
1D
0C
0?
1A
0@
1'
1&
1%
1$
#252
b1 )
b1 #
b11111111111111111111111111111110 *
b1110 -
15
0;
1?
0A
1@
0'
#254
b10 )
b10 #
b11111111111111111111111111111101 *
b1101 -
14
05
1;
0:
1B
0D
1C
0?
1A
0@
1'
0&
#256
b11 )
b11 #
b11111111111111111111111111111100 *
b1100 -
15
0;
1?
0A
1@
0'
#258
b100 )
b100 #
b11111111111111111111111111111011 *
b1011 -
13
04
05
1;
1:
09
1E
0G
1F
0B
1D
0C
0?
1A
0@
1'
1&
0%
#260
b101 )
b101 #
b11111111111111111111111111111010 *
b1010 -
15
0;
1?
0A
1@
0'
#262
b110 )
b110 #
b11111111111111111111111111111001 *
b1001 -
14
05
1;
0:
1B
0D
1C
0?
1A
0@
1'
0&
#264
b111 )
b111 #
b11111111111111111111111111111000 *
b1000 -
15
0;
1?
0A
1@
0'
#266
b1000 )
b0 (
b11111111111111111111111111111000 )
b0 "
b1000 #
b1000 *
12
03
04
05
0.
0/
00
01
1?
1@
1<
1B
1C
1=
1E
1F
1>
0H
0J
07
1;
1:
19
08
1$
0%
#267
1,
#268
b11111111111111111111111111111001 )
b1001 #
b111 *
b111 -
15
0;
0?
0@
0<
1&
0C
0=
1'
1%
0F
0>
0$
#269
0,
#270
b11111111111111111111111111111010 )
b1010 #
b110 *
b110 -
14
05
1;
0:
0B
1?
1@
1<
0'
#272
b11111111111111111111111111111011 )
b1011 #
b101 *
b101 -
15
0;
0?
0@
0<
0&
1'
#274
b11111111111111111111111111111100 )
b1100 #
b100 *
b100 -
13
04
05
1;
1:
09
0E
1B
1?
1@
1<
1C
1=
0'
#276
b11111111111111111111111111111101 )
b1101 #
b11 *
b11 -
15
0;
0?
0@
0<
1&
0C
0=
1'
0%
#278
b11111111111111111111111111111110 )
b1110 #
b10 *
b10 -
14
05
1;
0:
0B
1?
1@
1<
0'
#280
b11111111111111111111111111111111 )
b1111 #
b1 *
b1 -
15
0;
0?
0@
0<
0&
1'
#282
b0 )
b0 #
b0 *
b0 -
02
03
04
05
1;
1:
19
18
1H
1E
1B
1?
1@
1<
1C
1=
0'
0$
1F
1>
1I
17
#284
b1 )
b1 #
b11111111111111111111111111111111 *
b1111 -
15
0;
0?
0@
0<
1&
0C
0=
1'
1%
0F
0>
1$
0I
07
#286
b10 )
b10 #
b11111111111111111111111111111110 *
b1110 -
14
05
1;
0:
0B
1?
1@
1<
0'
#288
b11 )
b11 #
b11111111111111111111111111111101 *
b1101 -
15
0;
0?
0@
0<
0&
1'
#290
b100 )
b100 #
b11111111111111111111111111111100 *
b1100 -
13
04
05
1;
1:
09
0E
1B
1?
1@
1<
1C
1=
0'
#292
b101 )
b101 #
b11111111111111111111111111111011 *
b1011 -
15
0;
0?
0@
0<
1&
0C
0=
1'
0%
#294
b110 )
b110 #
b11111111111111111111111111111010 *
b1010 -
14
05
1;
0:
0B
1?
1@
1<
0'
#296
b111 )
b111 #
b11111111111111111111111111111001 *
b1001 -
15
0;
0?
0@
0<
0&
1'
#298
b1000 )
b1 (
b11111111111111111111111111111000 )
b1 "
b1000 #
b1001 *
12
03
04
05
11
0?
0@
1<
1;
1:
19
08
0H
1E
1B
1A
1C
1=
1F
1>
#299
1,
#300
b11111111111111111111111111111001 )
b1001 #
b1000 *
b1000 -
15
0;
1?
0A
1@
0'
#302
b11111111111111111111111111111010 )
b1010 #
b111 *
b111 -
14
05
1;
0:
0B
0C
0=
0?
1A
0@
1'
1%
0F
0>
1&
0$
#303
0,
#304
b11111111111111111111111111111011 )
b1011 #
b110 *
b110 -
15
0;
1?
0A
1@
0'
#306
b11111111111111111111111111111100 )
b1100 #
b101 *
b101 -
13
04
05
1;
1:
09
0E
1B
1C
1=
0?
1A
0@
1'
0&
#308
b11111111111111111111111111111101 )
b1101 #
b100 *
b100 -
15
0;
1?
0A
1@
0'
#310
b11111111111111111111111111111110 )
b1110 #
b11 *
b11 -
14
05
1;
0:
0B
0C
0=
0?
1A
0@
1'
0%
1&
#312
b11111111111111111111111111111111 )
b1111 #
b10 *
b10 -
15
0;
1?
0A
1@
0'
#314
b0 )
b0 #
b1 *
b1 -
02
03
04
05
1;
1:
19
18
1H
1E
1B
1C
1=
0?
1A
0@
1'
1F
1>
0&
1I
17
#316
b1 )
b1 #
b0 *
b0 -
15
0;
1?
0A
1@
0'
#318
b10 )
b10 #
b11111111111111111111111111111111 *
b1111 -
14
05
1;
0:
0B
0C
0=
0?
1A
0@
1'
1%
0F
0>
1&
1$
0I
07
#320
b11 )
b11 #
b11111111111111111111111111111110 *
b1110 -
15
0;
1?
0A
1@
0'
#322
b100 )
b100 #
b11111111111111111111111111111101 *
b1101 -
13
04
05
1;
1:
09
0E
1B
1C
1=
0?
1A
0@
1'
0&
#324
b101 )
b101 #
b11111111111111111111111111111100 *
b1100 -
15
0;
1?
0A
1@
0'
#326
b110 )
b110 #
b11111111111111111111111111111011 *
b1011 -
14
05
1;
0:
0B
0C
0=
0?
1A
0@
1'
0%
1&
#328
b111 )
b111 #
b11111111111111111111111111111010 *
b1010 -
15
0;
1?
0A
1@
0'
#330
b1000 )
b10 (
b11111111111111111111111111111000 )
b10 "
b1000 #
b1010 *
12
03
04
05
10
01
1?
1@
1<
0B
1;
1:
19
08
0H
1E
1D
1=
1F
1>
#331
1,
#332
b11111111111111111111111111111001 )
b1001 #
b1001 *
b1001 -
15
0;
0?
0@
0<
0&
1'
#334
b11111111111111111111111111111010 )
b1010 #
b1000 *
b1000 -
14
05
1;
0:
1B
0D
1=
1?
1@
1<
1C
0'
#336
b11111111111111111111111111111011 )
b1011 #
b111 *
b111 -
15
0;
0?
0@
0<
1&
0C
0=
1'
1%
0F
0>
0$
#337
0,
#338
b11111111111111111111111111111100 )
b1100 #
b110 *
b110 -
13
04
05
1;
1:
09
0E
0B
1D
1=
1?
1@
1<
0'
#340
b11111111111111111111111111111101 )
b1101 #
b101 *
b101 -
15
0;
0?
0@
0<
0&
1'
#342
b11111111111111111111111111111110 )
b1110 #
b100 *
b100 -
14
05
1;
0:
1B
0D
1=
1?
1@
1<
1C
0'
#344
b11111111111111111111111111111111 )
b1111 #
b11 *
b11 -
15
0;
0?
0@
0<
1&
0C
0=
1'
0%
